surroundingkeys/README.MD
surroundingkeys/__init__.py
surroundingkeys/kbda1.pkl
surroundingkeys/kbda2.pkl
surroundingkeys/kbda3.pkl
surroundingkeys/kbdadlm.pkl
surroundingkeys/kbdal.pkl
surroundingkeys/kbdarme.pkl
surroundingkeys/kbdarmph.pkl
surroundingkeys/kbdarmty.pkl
surroundingkeys/kbdarmw.pkl
surroundingkeys/kbdaze.pkl
surroundingkeys/kbdazel.pkl
surroundingkeys/kbdazst.pkl
surroundingkeys/kbdbash.pkl
surroundingkeys/kbdbe_1.pkl
surroundingkeys/kbdbe_2.pkl
surroundingkeys/kbdbene.pkl
surroundingkeys/kbdbgph.pkl
surroundingkeys/kbdbgph1.pkl
surroundingkeys/kbdbhc.pkl
surroundingkeys/kbdblr.pkl
surroundingkeys/kbdbr_1.pkl
surroundingkeys/kbdbr_2.pkl
surroundingkeys/kbdbu.pkl
surroundingkeys/kbdbug.pkl
surroundingkeys/kbdbulg.pkl
surroundingkeys/kbdca.pkl
surroundingkeys/kbdcan.pkl
surroundingkeys/kbdcher.pkl
surroundingkeys/kbdcherp.pkl
surroundingkeys/kbdcr_1.pkl
surroundingkeys/kbdcr_2.pkl
surroundingkeys/kbdcz.pkl
surroundingkeys/kbdcz1.pkl
surroundingkeys/kbdcz2.pkl
surroundingkeys/kbdda.pkl
surroundingkeys/kbddiv1.pkl
surroundingkeys/kbddiv2.pkl
surroundingkeys/kbddv.pkl
surroundingkeys/kbddzo.pkl
surroundingkeys/kbdes.pkl
surroundingkeys/kbdest.pkl
surroundingkeys/kbdfa.pkl
surroundingkeys/kbdfar.pkl
surroundingkeys/kbdfc.pkl
surroundingkeys/kbdfi.pkl
surroundingkeys/kbdfi1_1.pkl
surroundingkeys/kbdfi1_2.pkl
surroundingkeys/kbdfo.pkl
surroundingkeys/kbdfr.pkl
surroundingkeys/kbdfthrk.pkl
surroundingkeys/kbdgae.pkl
surroundingkeys/kbdgeo.pkl
surroundingkeys/kbdgeoer.pkl
surroundingkeys/kbdgeome.pkl
surroundingkeys/kbdgeooa.pkl
surroundingkeys/kbdgeoqw.pkl
surroundingkeys/kbdgkl.pkl
surroundingkeys/kbdgn.pkl
surroundingkeys/kbdgr.pkl
surroundingkeys/kbdgr1.pkl
surroundingkeys/kbdgrlnd.pkl
surroundingkeys/kbdgthc.pkl
surroundingkeys/kbdhau.pkl
surroundingkeys/kbdhaw.pkl
surroundingkeys/kbdhe.pkl
surroundingkeys/kbdhe220.pkl
surroundingkeys/kbdhe319.pkl
surroundingkeys/kbdheb.pkl
surroundingkeys/kbdhebl3.pkl
surroundingkeys/kbdhela2.pkl
surroundingkeys-0.10.dist-info/LICENSE.rst
surroundingkeys-0.10.dist-info/METADATA
surroundingkeys-0.10.dist-info/WHEEL
surroundingkeys-0.10.dist-info/top_level.txt
surroundingkeys-0.10.dist-info/RECORD
