Metadata-Version: 2.1
Name: surroundingkeys
Version: 0.10
Summary: Finds the closest neighboring keys of a given letter on a specific keyboard layout.
Home-page: https://github.com/hansalemaos/surroundingkeys
Author: Johannes Fischer
Author-email: aulasparticularesdealemaosp@gmail.com
License: MIT
Keywords: keyboard,neighbor
Classifier: Development Status :: 4 - Beta
Classifier: Programming Language :: Python :: 3 :: Only
Classifier: Programming Language :: Python :: 3.10
Classifier: Topic :: Software Development :: Libraries :: Python Modules
Classifier: Topic :: Utilities
License-File: LICENSE.rst
Requires-Dist: a-pandas-ex-closest-neighbours
Requires-Dist: cachetools
Requires-Dist: pandas
